MANIFEST.in
README.md
requirements.txt
setup.py
./qubit/__init__.py
./qubit/__main__.py
./qubit/config.py
./qubit/wsgiapp.py
./qubit/apis/__init__.py
./qubit/apis/mapreducer.py
./qubit/apis/qubit.py
./qubit/apis/spout.py
./qubit/apis/status.py
./qubit/apis/utils.py
./qubit/core/__init__.py
./qubit/core/app.py
./qubit/core/consts.py
./qubit/core/exceptions.py
./qubit/io/__init__.py
./qubit/io/celery/__init__.py
./qubit/io/celery/config.py
./qubit/io/celery/types.py
./qubit/io/celery/utils.py
./qubit/io/postgres/__init__.py
./qubit/io/postgres/postgres.py
./qubit/io/postgres/queryset.py
./qubit/io/postgres/types.py
./qubit/io/postgres/utils.py
./qubit/io/redis/__init__.py
./qubit/types/__init__.py
./qubit/types/function.py
./qubit/types/mapper.py
./qubit/types/mapreduce.py
./qubit/types/qubit.py
./qubit/types/reducer.py
./qubit/types/spout.py
./schema/__init__.py
./schema/utils.py
./tests/apis/__init__.py
./tests/apis/test_spout.py
./tests/io/__init__.py
./tests/io/test_db.py
./tests/io/test_schema.py
./tests/types/__init__.py
./tests/types/test_crud.py
qubit.egg-info/PKG-INFO
qubit.egg-info/SOURCES.txt
qubit.egg-info/dependency_links.txt
qubit.egg-info/entry_points.txt
qubit.egg-info/requires.txt
qubit.egg-info/top_level.txt