Metadata-Version: 1.1
Name: qubit
Version: 0.0.1
Summary: qubit.
Home-page: UNKNOWN
Author: ryankung
Author-email: ryankung@ieee.org
License: MIT
Platform: any
Classifier: Intended Audience :: Developers
Classifier: Programming Language :: Python
Classifier: Topic :: Software Development :: Libraries :: Python Modules
